{
  "games": [
    {
      "id": 1,
      "name": "Counter-Strike 2",
      "date": "2024-01-01",
      "gameicon": "https://cdn2.steamgriddb.com/icon/e1bd06c3f8089e7552aa0552cb387c92/32/512x512.png",
      "playtime": 120,
      "isDownload": false,
      "category": "favorite",
      "gridPhoto": "https://static1.cbrimages.com/wordpress/wp-content/uploads/2023/03/counter-strike-2.jpg",
      "lasttwoweeks": 33,
      "gameDetailPhoto": "https://cdn2.steamgriddb.com/hero_thumb/155cce39112748579e46da788c7c53f7.jpg",
      "achievement": 44,
      "totalachievement": 122,
      "size": 150000,
      "isInProgress": false,
      "inQueue": false,
      "resize": 51000,
      "reid": 1000
    },
    {
      "id": 2,
      "name": "Dota 2",
      "date": "2024-01-02",
      "gameicon": "https://cdn2.steamgriddb.com/icon/db98dc0dbafde48e8f74c0de001d35e4/32/128x128.png",
      "playtime": 140,
      "isDownload": false,
      "category": "favorite",
      "gridPhoto": "https://cdn2.steamgriddb.com/thumb/ccc5dd5279b84a232c60ea1bb5cf8519.jpg",
      "lasttwoweeks": 109,
      "gameDetailPhoto": "https://cdn2.steamgriddb.com/hero_thumb/82b02f59d83397a4f6851822234ef138.jpg",
      "achievement": 36,
      "totalachievement": 81,
      "size": 20185,
      "isInProgress": false,
      "inQueue": false,
      "resize": 0,
      "reid": 1001
    },
    {
      "id": 3,
      "name": "PUBG: Battlegrounds",
      "date": "2024-01-03",
      "gameicon": "https://cdn2.steamgriddb.com/icon/64c2d22899f32ccd5b3d9fca3ff04c9c/32/256x256.png",
      "playtime": 200,
      "isDownload": true,
      "category": "favorite",
      "gridPhoto": "https://cdn2.steamgriddb.com/thumb/577b1f6b27b99fa14d999e0ab21ea907.jpg",
      "lasttwoweeks": 149,
      "gameDetailPhoto": "https://cdn2.steamgriddb.com/hero_thumb/9697361bd81c04fb4ea891d63104a5a3.jpg",
      "achievement": 14,
      "totalachievement": 47,
      "size": 20677,
      "isInProgress": false,
      "inQueue": false,
      "resize": 14490,
      "reid": 1002
    },
    {
      "id": 4,
      "name": "NARAKA: BLADEPOINT",
      "date": "2024-01-04",
      "gameicon": "https://cdn2.steamgriddb.com/icon_thumb/7da8cfbdd6bebb76e383c1ecf334e522.png",
      "playtime": 180,
      "isDownload": true,
      "category": "favorite",
      "gridPhoto": "https://cdn2.steamgriddb.com/thumb/985c751b28318a5c5746834a0f26e050.jpg",
      "lasttwoweeks": 48,
      "gameDetailPhoto": "https://cdn2.steamgriddb.com/hero_thumb/9f36a921c26b879747bb6c172907d903.jpg",
      "achievement": 62,
      "totalachievement": 103,
      "size": 75270,
      "isInProgress": false,
      "inQueue": false,
      "resize": 0,
      "reid": 1003
    },
    {
      "id": 5,
      "name": "ELDEN RING",
      "date": "2024-01-05",
      "gameicon": "https://cdn2.steamgriddb.com/icon/0b99dab71519032b917dc641cdd7ac5b/32/256x256.png",
      "playtime": 160,
      "isDownload": false,
      "category": "favorite",
      "gridPhoto": "https://cdn2.steamgriddb.com/thumb/b7dc60f5a597d2a0687c2c43a3cd3417.jpg",
      "lasttwoweeks": 52,
      "gameDetailPhoto": "https://cdn2.steamgriddb.com/hero_thumb/d1fcdf15cb97c47d0ed1e1e10773ae36.jpg",
      "achievement": 24,
      "totalachievement": 68,
      "size": 67676,
      "isInProgress": false,
      "inQueue": false,
      "resize": 0,
      "reid": 1004
    },
    {
      "id": 6,
      "name": "Team Fortress 2",
      "date": "2024-01-06",
      "gameicon": "https://cdn2.steamgriddb.com/icon_thumb/e9257036daf20f062a498aab563d7712.png",
      "playtime": 150,
      "isDownload": false,
      "category": "2d",
      "gridPhoto": "https://cdn2.steamgriddb.com/thumb/341f73f21eb3842764224578c161e2cc.jpg",
      "lasttwoweeks": 109,
      "gameDetailPhoto": "https://cdn2.steamgriddb.com/hero_thumb/c6e9701b682ec8f4cc3f8923c1dbb1f8.jpg",
      "achievement": 1,
      "totalachievement": 3,
      "size": 79242,
      "isInProgress": false,
      "inQueue": false,
      "resize": 0,
      "reid": 1005
    },
    {
      "id": 7,
      "name": "Apex Legends",
      "date": "2024-01-07",
      "gameicon": "https://cdn2.steamgriddb.com/icon/5774b6bb3970f53874a09e9eec130980/32/512x512.png",
      "playtime": 130,
      "isDownload": false,
      "category": "uncategorized",
      "gridPhoto": "https://cdn2.steamgriddb.com/thumb/7462d99d60e1fb77bf39840c19c44e6e.jpg",
      "lasttwoweeks": 40,
      "gameDetailPhoto": "https://cdn2.steamgriddb.com/hero_thumb/991327d63593b0ba2c45618bf81f6a64.jpg",
      "achievement": 49,
      "totalachievement": 124,
      "size": 85782,
      "isInProgress": false,
      "inQueue": false,
      "resize": 0,
      "reid": 1006
    },
    {
      "id": 8,
      "name": "The First Descendant",
      "date": "2024-01-08",
      "gameicon": "https://cdn2.steamgriddb.com/icon/74e3932c1af80284b053e195c2dbe0cd/32/256x256.png",
      "playtime": 110,
      "isDownload": false,
      "category": "uncategorized",
      "gridPhoto": "https://cdn2.steamgriddb.com/thumb/dfbab00a7961b194155ddc8b625179c1.jpg",
      "lasttwoweeks": 58,
      "gameDetailPhoto": "https://cdn2.steamgriddb.com/hero_thumb/972afb36f431249abc42e52785e841ec.jpg",
      "achievement": 27,
      "totalachievement": 115,
      "size": 21916,
      "isInProgress": false,
      "inQueue": false,
      "resize": 0,
      "reid": 1007
    },
    {
      "id": 9,
      "name": "Grand Theft Auto V",
      "date": "2024-01-09",
      "gameicon": "https://cdn2.steamgriddb.com/icon/84ddfb34126fc3a48ee38d7044e87276/32/256x256.png",
      "playtime": 100,
      "isDownload": false,
      "category": "favorite",
      "gridPhoto": "https://cdn2.steamgriddb.com/thumb/68ab8c7bbe4b7182b9dc959435ea896b.jpg",
      "lasttwoweeks": 16,
      "gameDetailPhoto": "https://cdn2.steamgriddb.com/hero_thumb/838aac83e00e8c5ca0f839c96d6cb3be.jpg",
      "achievement": 27,
      "totalachievement": 68,
      "size": 53391,
      "isInProgress": false,
      "inQueue": false,
      "resize": 0,
      "reid": 1008
    },
    {
      "id": 10,
      "name": "Stardew Valley",
      "date": "2024-01-10",
      "gameicon": "https://cdn2.steamgriddb.com/icon/7a6f5f6a69fe900cda205b8c2d811cd4/4/48x48.png",
      "playtime": 90,
      "isDownload": false,
      "category": "roleplay",
      "gridPhoto": "https://cdn2.steamgriddb.com/thumb/879d44be14b9a8441dd69d6421afa9f4.jpg",
      "lasttwoweeks": 53,
      "gameDetailPhoto": "https://cdn2.steamgriddb.com/hero_thumb/d44c78dcad9de0aed2f37902ea02cef2.png",
      "achievement": 6,
      "totalachievement": 11,
      "size": 46722,
      "isInProgress": false,
      "inQueue": false,
      "resize": 0,
      "reid": 1009
    },
    {
      "id": 11,
      "name": "Wallpaper Engine",
      "date": "2024-01-11",
      "gameicon": "https://cdn2.steamgriddb.com/icon_thumb/2611fdd1a2a998be4d3af1466d41d9d1.png",
      "playtime": 80,
      "isDownload": false,
      "category": "uncategorized",
      "gridPhoto": "https://cdn2.steamgriddb.com/thumb/2046e4fc6f92ae6657d213cc0590d2d7.jpg",
      "lasttwoweeks": 80,
      "gameDetailPhoto": "https://cdn2.steamgriddb.com/hero_thumb/07ebae5de4be22e8d3916839a654d94a.jpg",
      "achievement": 38,
      "totalachievement": 68,
      "size": 19406,
      "isInProgress": false,
      "inQueue": false,
      "resize": 0,
      "reid": 1010
    },
    {
      "id": 12,
      "name": "Once Human",
      "date": "2024-01-12",
      "gameicon": "https://i.hizliresim.com/i5ktw11.png",
      "playtime": 70,
      "isDownload": false,
      "category": "uncategorized",
      "gridPhoto": "https://cdn2.steamgriddb.com/thumb/b45a258c2494e8dca1ca7353148d468b.jpg",
      "lasttwoweeks": 10,
      "gameDetailPhoto": "https://cdn2.steamgriddb.com/hero_thumb/797c8448062aa46c547c0434e481bc62.jpg",
      "achievement": 4,
      "totalachievement": 6,
      "size": 74130,
      "isInProgress": false,
      "inQueue": false,
      "resize": 0,
      "reid": 1011
    },
    {
      "id": 13,
      "name": "Rust",
      "date": "2024-01-13",
      "gameicon": "https://cdn2.steamgriddb.com/icon/1098f40d613dcadb0486a71293cb6e31/32/256x256.png",
      "playtime": 60,
      "isDownload": false,
      "category": "uncategorized",
      "gridPhoto": "https://cdn2.steamgriddb.com/thumb/56b65e3fa7ff454b04af61f18072680b.jpg",
      "lasttwoweeks": 13,
      "gameDetailPhoto": "https://cdn2.steamgriddb.com/hero_thumb/7ff7ca9cc8db185788a6054737e03afb.jpg",
      "achievement": 3,
      "totalachievement": 13,
      "size": 55040,
      "isInProgress": false,
      "inQueue": false,
      "resize": 0,
      "reid": 1012
    },
    {
      "id": 14,
      "name": "Crab Game",
      "date": "2024-01-14",
      "gameicon": "https://cdn2.steamgriddb.com/grid/55f7541b23678fb1db79b424cf163b49.png",
      "playtime": 50,
      "isDownload": false,
      "category": "roleplay",
      "gridPhoto": "https://cdn2.steamgriddb.com/thumb/dbd3a273beabaf841fbd9bc21a2bfd67.jpg",
      "lasttwoweeks": 27,
      "gameDetailPhoto": "https://cdn2.steamgriddb.com/hero_thumb/e8520871e749a7ea9fb362d1805f28be.jpg",
      "achievement": 14,
      "totalachievement": 32,
      "size": 18288,
      "isInProgress": false,
      "inQueue": false,
      "resize": 0,
      "reid": 1013
    },
    {
      "id": 15,
      "name": "Palworld",
      "date": "2024-01-15",
      "gameicon": "https://cdn2.steamgriddb.com/icon_thumb/87b0cba64000c51c883f57274c04519c.png",
      "playtime": 40,
      "isDownload": false,
      "category": "uncategorized",
      "gridPhoto": "https://cdn2.steamgriddb.com/thumb/f261398362af8cbc3321e8c7401867c6.png",
      "lasttwoweeks": 7,
      "gameDetailPhoto": "https://cdn2.steamgriddb.com/hero_thumb/9cb9addcfcd3dc9f950f27025ef20fdc.jpg",
      "achievement": 119,
      "totalachievement": 144,
      "size": 83211,
      "isInProgress": false,
      "inQueue": false,
      "resize": 0,
      "reid": 1014
    },
    {
      "id": 16,
      "name": "Destiny 2",
      "date": "2024-01-16",
      "gameicon": "https://cdn2.steamgriddb.com/icon/9908279ebbf1f9b250ba689db6a0222b/32/256x256.png",
      "playtime": 30,
      "isDownload": false,
      "category": "uncategorized",
      "gridPhoto": "https://cdn2.steamgriddb.com/thumb/ed0ffe44fefcf1ae95176bd0c917d840.jpg",
      "lasttwoweeks": 23,
      "gameDetailPhoto": "https://cdn2.steamgriddb.com/hero_thumb/e1740c5223422374b7fb1888478aabb9.jpg",
      "achievement": 5,
      "totalachievement": 56,
      "size": 11230,
      "isInProgress": false,
      "inQueue": false,
      "resize": 0,
      "reid": 1015
    },
    {
      "id": 17,
      "name": "Sid Meier's Civilization VI",
      "date": "2024-01-17",
      "gameicon": "https://cdn2.steamgriddb.com/icon_thumb/ec345c4ea8758243dc3d1424ff9f86b1.png",
      "playtime": 20,
      "isDownload": false,
      "category": "fps",
      "gridPhoto": "https://cdn2.steamgriddb.com/thumb/124ab1affbb8414a719a7d68015fe3a1.jpg",
      "lasttwoweeks": 12,
      "gameDetailPhoto": "https://cdn2.steamgriddb.com/hero_thumb/c6862d63b17d713ee14f3a405d9fde77.jpg",
      "achievement": 47,
      "totalachievement": 95,
      "size": 17346,
      "isInProgress": false,
      "inQueue": false,
      "resize": 0,
      "reid": 1016
    },
    {
      "id": 18,
      "name": "War Thunder",
      "date": "2024-01-18",
      "gameicon": "https://cdn2.steamgriddb.com/icon/a8f9c922be3d2559a3b6da1429bc1301/32/256x256.png",
      "playtime": 10,
      "isDownload": false,
      "category": "uncategorized",
      "gridPhoto": "https://cdn2.steamgriddb.com/thumb/22e2f01322e89a725ba98d77f0feec85.jpg",
      "lasttwoweeks": 6,
      "gameDetailPhoto": "https://cdn2.steamgriddb.com/hero_thumb/91f2b67df684436c15d168cabaca4f92.jpg",
      "achievement": 47,
      "totalachievement": 111,
      "size": 40477,
      "isInProgress": false,
      "inQueue": false,
      "resize": 0,
      "reid": 1017
    },
    {
      "id": 19,
      "name": "Call of Duty",
      "date": "2024-01-19",
      "gameicon": "https://cdn2.steamgriddb.com/icon_thumb/f1e709e6aef16ba2f0cd6c7e4f52b9b6.png",
      "playtime": 25,
      "isDownload": false,
      "category": "uncategorized",
      "gridPhoto": "https://cdn2.steamgriddb.com/thumb/abc08456cfdc28e5ae109e8898eabf29.jpg",
      "lasttwoweeks": 1,
      "gameDetailPhoto": "https://cdn2.steamgriddb.com/hero_thumb/43d1e4f821fc02813f594e852f0c59b6.jpg",
      "achievement": 29,
      "totalachievement": 83,
      "size": 55285,
      "isInProgress": false,
      "inQueue": false,
      "resize": 0,
      "reid": 1018
    },
    {
      "id": 20,
      "name": "Baldur's Gate 3",
      "date": "2024-01-20",
      "gameicon": "https://cdn2.steamgriddb.com/icon/0cd60efb5578cd967c3c23894f305800/32/256x256.png",
      "playtime": 35,
      "isDownload": false,
      "category": "uncategorized",
      "gridPhoto": "https://cdn2.steamgriddb.com/thumb/6b23f8c69f181d832d041d2cc96c0bce.jpg",
      "lasttwoweeks": 5,
      "gameDetailPhoto": "https://cdn2.steamgriddb.com/hero_thumb/eac419c3f4586033d7f719314a102ea3.jpg",
      "achievement": 14,
      "totalachievement": 62,
      "size": 50638,
      "isInProgress": false,
      "inQueue": false,
      "resize": 0,
      "reid": 1019
    },
    {
      "id": 21,
      "name": "EA SPORTS FC 24",
      "date": "2024-01-21",
      "gameicon": "https://cdn2.steamgriddb.com/icon/f33dc5483be5538172f6e326dc2a4266/32/256x256.png",
      "playtime": 45,
      "isDownload": false,
      "category": "favorite",
      "gridPhoto": "https://cdn2.steamgriddb.com/thumb/9f1b884f0ed6b4ef0e056c453ff20258.jpg",
      "lasttwoweeks": 27,
      "gameDetailPhoto": "https://cdn2.steamgriddb.com/hero_thumb/3bd8fdb090f1f5eb66a00c84dbc5ad51.jpg",
      "achievement": 16,
      "totalachievement": 24,
      "size": 84083,
      "isInProgress": false,
      "inQueue": false,
      "resize": 0,
      "reid": 1020
    },
    {
      "id": 22,
      "name": "Tom Clancy's Rainbow Six Siege",
      "date": "2024-01-22",
      "gameicon": "https://cdn2.steamgriddb.com/icon/1387a00f03b4b423e63127b08c261bdc/32/256x256.png",
      "playtime": 55,
      "isDownload": false,
      "category": "favorite",
      "gridPhoto": "https://cdn2.steamgriddb.com/thumb/8a1e436c080d7ac797ff9779367e3dcd.jpg",
      "lasttwoweeks": 11,
      "gameDetailPhoto": "https://cdn2.steamgriddb.com/hero_thumb/68ab14b322fecf44196cc1186f167857.jpg",
      "achievement": 37,
      "totalachievement": 47,
      "size": 80542,
      "isInProgress": false,
      "inQueue": false,
      "resize": 20125,
      "reid": 1021
    },
    {
      "id": 23,
      "name": "Football Manager 2024",
      "date": "2024-01-23",
      "gameicon": "https://i.hizliresim.com/iyepw59.jpg",
      "playtime": 65,
      "isDownload": true,
      "category": "favorite",
      "gridPhoto": "https://cdn2.steamgriddb.com/thumb/e7508e16b762bdab8d76f7fb989a9b74.jpg",
      "lasttwoweeks": 35,
      "gameDetailPhoto": "https://cdn2.steamgriddb.com/hero_thumb/66cfbed07520703958406a8e6b8e7057.jpg",
      "achievement": 12,
      "totalachievement": 43,
      "size": 22175,
      "isInProgress": false,
      "inQueue": false,
      "resize": 2220,
      "reid": 1022
    },
    {
      "id": 24,
      "name": "Don't Starve Together",
      "date": "2024-01-24",
      "gameicon": "https://cdn2.steamgriddb.com/icon_thumb/f18e1e190060ee0af7d043f41d1f28df.png",
      "playtime": 75,
      "isDownload": false,
      "category": "favorite",
      "gridPhoto": "https://cdn2.steamgriddb.com/thumb/433206a957cc9824ced79a5060e7918c.jpg",
      "lasttwoweeks": 54,
      "gameDetailPhoto": "https://cdn2.steamgriddb.com/hero_thumb/dfe0c74a3f265edd7b90e43990e70b00.jpg",
      "achievement": 0,
      "totalachievement": 40,
      "size": 113675,
      "isInProgress": false,
      "inQueue": false,
      "resize": 0,
      "reid": 1023
    },
    {
      "id": 25,
      "name": "Monster Hunter: World",
      "date": "2024-01-25",
      "gameicon": "https://cdn2.steamgriddb.com/icon_thumb/c95d62c68196b2d0c1c1de8c7eeb6d50.png",
      "playtime": 85,
      "isDownload": false,
      "category": "uncategorized",
      "gridPhoto": "https://cdn2.steamgriddb.com/thumb/83f0554c36a17bbd49a3ec6306b33eda.jpg",
      "lasttwoweeks": 1,
      "gameDetailPhoto": "https://cdn2.steamgriddb.com/hero_thumb/9da3bbc7c90afeae7fe153b1ff238c35.jpg",
      "achievement": 62,
      "totalachievement": 77,
      "size": 109267,
      "isInProgress": false,
      "inQueue": false,
      "resize": 0,
      "reid": 1024
    },
    {
      "id": 26,
      "name": "FINAL FANTASY XIV Online",
      "date": "2024-01-26",
      "gameicon": "https://cdn2.steamgriddb.com/icon/384356f782d932ac1dcaf8a4e67ac041/32/256x256.png",
      "playtime": 95,
      "isDownload": false,
      "category": "2d",
      "gridPhoto": "https://cdn2.steamgriddb.com/thumb/88a7ec027f387807d2ff4059b09764c1.jpg",
      "lasttwoweeks": 3,
      "gameDetailPhoto": "https://cdn2.steamgriddb.com/hero_thumb/b075703bbe07a50ddcccfaac424bb6d9.jpg",
      "achievement": 19,
      "totalachievement": 40,
      "size": 39676,
      "isInProgress": false,
      "inQueue": false,
      "resize": 0,
      "reid": 1025
    },
    {
      "id": 27,
      "name": "7 Days to Die",
      "date": "2024-01-27",
      "gameicon": "https://cdn2.steamgriddb.com/icon/384356f782d932ac1dcaf8a4e67ac041/32/256x256.png",
      "playtime": 105,
      "isDownload": false,
      "category": "fps",
      "gridPhoto": "https://cdn2.steamgriddb.com/thumb/86957c42cdcb48d61333735dd6c22312.jpg",
      "lasttwoweeks": 66,
      "gameDetailPhoto": "https://cdn2.steamgriddb.com/hero_thumb/c2e1767dee0b00aadf6f4a087ea182f9.jpg",
      "achievement": 41,
      "totalachievement": 59,
      "size": 29155,
      "isInProgress": false,
      "inQueue": false,
      "resize": 0,
      "reid": 1026
    },
    {
      "id": 28,
      "name": "Dead by Daylight",
      "date": "2024-01-28",
      "gameicon": "https://cdn2.steamgriddb.com/icon_thumb/735ddec196a9ca5745c05bec0eaa4bf9.png",
      "playtime": 115,
      "isDownload": false,
      "category": "roleplay",
      "gridPhoto": "https://cdn2.steamgriddb.com/thumb/985869618b4b5faf733f6971015c8420.jpg",
      "lasttwoweeks": 50,
      "gameDetailPhoto": "https://cdn2.steamgriddb.com/hero_thumb/947f1a3a5122ba00b91e95a516295359.jpg",
      "achievement": 23,
      "totalachievement": 96,
      "size": 105127,
      "isInProgress": false,
      "inQueue": false,
      "resize": 0,
      "reid": 1027
    },
    {
      "id": 29,
      "name": "VRChat",
      "date": "2024-01-29",
      "gameicon": "https://cdn2.steamgriddb.com/icon/4b0a618db23379c7c77f818cf569050d/32/256x256.png",
      "playtime": 125,
      "isDownload": false,
      "category": "uncategorized",
      "gridPhoto": "https://cdn2.steamgriddb.com/thumb/36deb46b8a06e33e4c96036ff9bdabd0.jpg",
      "lasttwoweeks": 110,
      "gameDetailPhoto": "https://cdn2.steamgriddb.com/hero_thumb/db85e2590b6109813dafa101ceb2faeb.jpg",
      "achievement": 2,
      "totalachievement": 5,
      "size": 27106,
      "isInProgress": false,
      "inQueue": false,
      "resize": 0,
      "reid": 1028
    },
    {
      "id": 30,
      "name": "Chained Together",
      "date": "2024-01-30",
      "gameicon": "https://cdn2.steamgriddb.com/icon/f6c5d3cfc2a8301e92959f0243eabf65/32/256x256.png",
      "playtime": 135,
      "isDownload": false,
      "category": "roleplay",
      "gridPhoto": "https://cdn2.steamgriddb.com/thumb/a11d7446f9629ca4831b16315bb5f6a0.jpg",
      "lasttwoweeks": 121,
      "gameDetailPhoto": "https://cdn2.steamgriddb.com/hero_thumb/9f2b7ead1dd49e2307704383f891890a.jpg",
      "achievement": 20,
      "totalachievement": 25,
      "size": 20396,
      "isInProgress": false,
      "inQueue": false,
      "resize": 0,
      "reid": 1029
    },
    {
      "id": 31,
      "name": "Left 4 Dead 2",
      "date": "2024-01-31",
      "gameicon": "https://cdn2.steamgriddb.com/icon/cf9a242b70f45317ffd281241fa66502/32/256x256.png",
      "playtime": 145,
      "isDownload": false,
      "category": "2d",
      "gridPhoto": "https://cdn2.steamgriddb.com/thumb/7f1e5e564d968306e6b522c51a083545.jpg",
      "lasttwoweeks": 53,
      "gameDetailPhoto": "https://cdn2.steamgriddb.com/hero_thumb/e06015c0688508d35fc02b0434cb7ce9.jpg",
      "achievement": 13,
      "totalachievement": 76,
      "size": 18690,
      "isInProgress": false,
      "inQueue": false,
      "resize": 0,
      "reid": 1030
    },
    {
      "id": 32,
      "name": "Dark and Darker",
      "date": "2024-02-01",
      "gameicon": "https://cdn2.steamgriddb.com/icon_thumb/f53203e7da73bf0970140a39c986231f.png",
      "playtime": 155,
      "isDownload": false,
      "category": "uncategorized",
      "gridPhoto": "https://cdn2.steamgriddb.com/thumb/ae5a2e7265ddd03606e527853c53163a.png",
      "lasttwoweeks": 110,
      "gameDetailPhoto": "https://cdn2.steamgriddb.com/hero_thumb/a56ee11d03e067e9b5d626098bb82572.jpg",
      "achievement": 51,
      "totalachievement": 133,
      "size": 21310,
      "isInProgress": false,
      "inQueue": false,
      "resize": 0,
      "reid": 1031
    },
    {
      "id": 33,
      "name": "Battlefield V",
      "date": "2024-02-02",
      "gameicon": "https://cdn2.steamgriddb.com/icon_thumb/a8e864d04c95572d1aece099af852d0a.png",
      "playtime": 165,
      "isDownload": true,
      "category": "favorite",
      "gridPhoto": "https://cdn2.steamgriddb.com/thumb/6d44d555d66bef025eb4c4f3b0355fc6.png",
      "lasttwoweeks": 50,
      "gameDetailPhoto": "https://cdn2.steamgriddb.com/hero_thumb/c9f0f895fb98ab9159f51fd0297e236d.jpg",
      "achievement": 11,
      "totalachievement": 33,
      "size": 30504,
      "isInProgress": false,
      "inQueue": false,
      "resize": 0,
      "reid": 1032
    },
    {
      "id": 34,
      "name": "Terraria",
      "date": "2024-02-03",
      "gameicon": "https://cdn2.steamgriddb.com/icon_thumb/912b92ae7dbedd0344a6580a7b90efc6.png",
      "playtime": 175,
      "isDownload": false,
      "category": "uncategorized",
      "gridPhoto": "https://cdn2.steamgriddb.com/thumb/a149c01c1ae620d9aaac77c2ca28b8f2.jpg",
      "lasttwoweeks": 3,
      "gameDetailPhoto": "https://cdn2.steamgriddb.com/hero_thumb/38dadc9fae7b5a4415d01986ee4907fe.jpg",
      "achievement": 12,
      "totalachievement": 52,
      "size": 54289,
      "isInProgress": false,
      "inQueue": false,
      "resize": 0,
      "reid": 1033
    },
    {
      "id": 35,
      "name": "tModLoader",
      "date": "2024-02-04",
      "gameicon": "https://cdn2.steamgriddb.com/icon/16ad66b2d7d7eda19f34e2f6197e2236/32/256x256.png",
      "playtime": 185,
      "isDownload": false,
      "category": "uncategorized",
      "gridPhoto": "https://cdn2.steamgriddb.com/thumb/6e081e481b2635e5eae188c358c45a46.jpg",
      "lasttwoweeks": 104,
      "gameDetailPhoto": "https://cdn2.steamgriddb.com/hero_thumb/d36117508a7151033ca0322696b574db.jpg",
      "achievement": 24,
      "totalachievement": 81,
      "size": 26814,
      "isInProgress": false,
      "inQueue": false,
      "resize": 0,
      "reid": 1034
    },
    {
      "id": 36,
      "name": "Hearts of Iron IV",
      "date": "2024-02-05",
      "gameicon": "https://cdn2.steamgriddb.com/icon_thumb/e2d988c728d061b916697ba7f095f98c.png",
      "playtime": 195,
      "isDownload": false,
      "category": "uncategorized",
      "gridPhoto": "https://cdn2.steamgriddb.com/thumb/045be8a84fc71917f3f42b28b3e465bf.jpg",
      "lasttwoweeks": 104,
      "gameDetailPhoto": "https://cdn2.steamgriddb.com/hero_thumb/a76650df1a9ed5ae6c11bce464aa2710.jpg",
      "achievement": 5,
      "totalachievement": 82,
      "size": 74110,
      "isInProgress": false,
      "inQueue": false,
      "resize": 0,
      "reid": 1035
    },
    {
      "id": 37,
      "name": "Red Dead Redemption 2",
      "date": "2024-02-06",
      "gameicon": "https://cdn2.steamgriddb.com/icon/f6ad645a331d5e5e95938c1439ba385d/32/256x256.png",
      "playtime": 205,
      "isDownload": false,
      "category": "uncategorized",
      "gridPhoto": "https://cdn2.steamgriddb.com/thumb/af152754c14761f3b980571934d567b1.jpg",
      "lasttwoweeks": 164,
      "gameDetailPhoto": "https://cdn2.steamgriddb.com/hero_thumb/4b23f8dc9eb4ed500a662e396908d39b.png",
      "achievement": 3,
      "totalachievement": 4,
      "size": 64282,
      "isInProgress": false,
      "inQueue": false,
      "resize": 0,
      "reid": 1036
    },
    {
      "id": 38,
      "name": "Overwatch 2",
      "date": "2024-02-07",
      "gameicon": "https://cdn2.steamgriddb.com/icon_thumb/f812eab186eb17d72275bb38b918913d.png",
      "playtime": 215,
      "isDownload": false,
      "category": "roleplay",
      "gridPhoto": "https://cdn2.steamgriddb.com/thumb/99d9d07fbf4e638c5becbdaaa1b55dfa.jpg",
      "lasttwoweeks": 53,
      "gameDetailPhoto": "https://cdn2.steamgriddb.com/hero_thumb/f891846243ad469e801675dfb3da17b5.jpg",
      "achievement": 20,
      "totalachievement": 108,
      "size": 19552,
      "isInProgress": false,
      "inQueue": false,
      "resize": 0,
      "reid": 1037
    },
    {
      "id": 39,
      "name": "Cyberpunk 2077",
      "date": "2024-02-08",
      "gameicon": "https://cdn2.steamgriddb.com/icon/b3e3e393c77e35a4a3f3cbd1e429b5dc/32/256x256.png",
      "playtime": 225,
      "isDownload": true,
      "category": "favorite",
      "gridPhoto": "https://cdn2.steamgriddb.com/thumb/f5da749e8e6fcf505376389c4b0c1150.jpg",
      "lasttwoweeks": 183,
      "gameDetailPhoto": "https://cdn2.steamgriddb.com/hero_thumb/1d82e3e1aab5070e537de3d55beac634.jpg",
      "achievement": 33,
      "totalachievement": 76,
      "size": 20269,
      "isInProgress": false,
      "inQueue": false,
      "resize": 0,
      "reid": 1038
    },
    {
      "id": 40,
      "name": "Street Fighter 6",
      "date": "2024-02-09",
      "gameicon": "https://cdn2.steamgriddb.com/icon_thumb/6622392eb0d8dfdacc44c7f7397ce4ab.png",
      "playtime": 235,
      "isDownload": false,
      "category": "roleplay",
      "gridPhoto": "https://cdn2.steamgriddb.com/thumb/b1eb4bda53588c93285f37353b95a2ef.png",
      "lasttwoweeks": 121,
      "gameDetailPhoto": "https://cdn2.steamgriddb.com/hero_thumb/da195267d14e69aff6c92be320fee1fc.jpg",
      "achievement": 41,
      "totalachievement": 55,
      "size": 76102,
      "isInProgress": false,
      "inQueue": false,
      "resize": 0,
      "reid": 1039
    },
    {
      "id": 41,
      "name": "HELLDIVERS 2",
      "date": "2024-02-10",
      "gameicon": "https://cdn2.steamgriddb.com/icon/a6cf2b02bf0a6a7494bd13b1257ad2c2/32/256x256.png",
      "playtime": 245,
      "isDownload": false,
      "category": "fps",
      "gridPhoto": "https://cdn2.steamgriddb.com/thumb/fdce052902b92aa723ad71f5c978c18f.jpg",
      "lasttwoweeks": 236,
      "gameDetailPhoto": "https://cdn2.steamgriddb.com/hero_thumb/58a97c95c23b3d8e1567d444c1e024a0.jpg",
      "achievement": 12,
      "totalachievement": 23,
      "size": 62249,
      "isInProgress": false,
      "inQueue": false,
      "resize": 0,
      "reid": 1040
    },
    {
      "id": 42,
      "name": "DayZ",
      "date": "2024-02-11",
      "gameicon": "https://cdn2.steamgriddb.com/icon/8788fba6a40330756f59a37106b005d5/32/128x128.png",
      "playtime": 255,
      "isDownload": false,
      "category": "2d",
      "gridPhoto": "https://cdn2.steamgriddb.com/thumb/b54cf79ff86138fae5bfa8fa22aa6b8b.png",
      "lasttwoweeks": 166,
      "gameDetailPhoto": "https://cdn2.steamgriddb.com/hero_thumb/7bbb9477a17863c5f05695b754185377.jpg",
      "achievement": 54,
      "totalachievement": 132,
      "size": 10781,
      "isInProgress": false,
      "inQueue": false,
      "resize": 0,
      "reid": 1041
    },
    {
      "id": 43,
      "name": "Euro Truck Simulator 2",
      "date": "2024-02-12",
      "gameicon": "https://cdn2.steamgriddb.com/icon/86ebc43444cdf451b149e5de84ff3ef5/32/256x256.png",
      "playtime": 265,
      "isDownload": false,
      "category": "roleplay",
      "gridPhoto": "https://cdn2.steamgriddb.com/thumb/8227c2ce0e9af9745a927e89d6107994.jpg",
      "lasttwoweeks": 69,
      "gameDetailPhoto": "https://cdn2.steamgriddb.com/hero_thumb/6e716efd1ac524bbccbb5b57ee0e452a.jpg",
      "achievement": 13,
      "totalachievement": 31,
      "size": 45716,
      "isInProgress": false,
      "inQueue": false,
      "resize": 0,
      "reid": 1042
    },
    {
      "id": 44,
      "name": "Phasmophobia",
      "date": "2024-02-13",
      "gameicon": "https://cdn2.steamgriddb.com/icon/1b742ae215adf18b75449c6e272fd92d/32/1024x1024.png",
      "playtime": 275,
      "isDownload": false,
      "category": "uncategorized",
      "gridPhoto": "https://cdn2.steamgriddb.com/thumb/b8ee42f6c6733d5db34b17a5aaa5844d.jpg",
      "lasttwoweeks": 205,
      "gameDetailPhoto": "https://cdn2.steamgriddb.com/hero_thumb/16ec9e966c6f64a5ff54199e398d4b42.jpg",
      "achievement": 69,
      "totalachievement": 94,
      "size": 80672,
      "isInProgress": false,
      "inQueue": false,
      "resize": 0,
      "reid": 1043
    },
    {
      "id": 45,
      "name": "ARK: Survival Evolved",
      "date": "2024-02-14",
      "gameicon": "https://cdn2.steamgriddb.com/icon/3ec0e2c7f4536e7ce9e9ce183b1de9e8/32/256x256.png",
      "playtime": 285,
      "isDownload": false,
      "category": "roleplay",
      "gridPhoto": "https://cdn2.steamgriddb.com/thumb/917fb629a072adaa792fe3a16ac0bd08.jpg",
      "lasttwoweeks": 248,
      "gameDetailPhoto": "https://cdn2.steamgriddb.com/hero_thumb/c764c89e73f5be426bce2d42a72c2f1f.jpg",
      "achievement": 34,
      "totalachievement": 133,
      "size": 116344,
      "isInProgress": false,
      "inQueue": false,
      "resize": 0,
      "reid": 1044
    },
    {
      "id": 46,
      "name": "The Elder Scrolls V: Skyrim",
      "date": "2024-02-15",
      "gameicon": "https://cdn2.steamgriddb.com/icon_thumb/4b04a686b0ad13dce35fa99fa4161c65.png",
      "playtime": 295,
      "isDownload": false,
      "category": "roleplay",
      "gridPhoto": "https://cdn2.steamgriddb.com/thumb/cd9262c0ad6d5b7006a1a3a89aac26ae.jpg",
      "lasttwoweeks": 104,
      "gameDetailPhoto": "https://cdn2.steamgriddb.com/hero_thumb/a4267159aa970aa5a6542bcbb7ef575e.jpg",
      "achievement": 7,
      "totalachievement": 53,
      "size": 38653,
      "isInProgress": false,
      "inQueue": false,
      "resize": 0,
      "reid": 1045
    },
    {
      "id": 47,
      "name": "RimWorld",
      "date": "2024-02-16",
      "gameicon": "https://cdn2.steamgriddb.com/icon_thumb/d37eb50d868361ea729bb4147eb3c1d8.png",
      "playtime": 305,
      "isDownload": false,
      "category": "2d",
      "gridPhoto": "https://cdn2.steamgriddb.com/thumb/8efc5cd1d17433c026808e43149b0c9e.jpg",
      "lasttwoweeks": 182,
      "gameDetailPhoto": "https://cdn2.steamgriddb.com/hero_thumb/4501a48d6be19783cea78bd746415e4c.jpg",
      "achievement": 96,
      "totalachievement": 145,
      "size": 114942,
      "isInProgress": false,
      "inQueue": false,
      "resize": 0,
      "reid": 1046
    },
    {
      "id": 48,
      "name": "Sekiro: Shadows Die Twice",
      "date": "2024-02-17",
      "gameicon": "https://cdn2.steamgriddb.com/icon/72e0a400c7b6e0beb7f2992c5378b3f6/32/256x256.png",
      "playtime": 315,
      "isDownload": false,
      "category": "fps",
      "gridPhoto": "https://cdn2.steamgriddb.com/thumb/f857e90064a9f7fde6981aea8a5b8263.jpg",
      "lasttwoweeks": 155,
      "gameDetailPhoto": "https://cdn2.steamgriddb.com/hero_thumb/2ee2b71a912ddc28699435eca8bd6486.jpg",
      "achievement": 66,
      "totalachievement": 85,
      "size": 41514,
      "isInProgress": false,
      "inQueue": false,
      "resize": 0,
      "reid": 1047
    },
    {
      "id": 49,
      "name": "The Witcher 3: Wild Hunt",
      "date": "2024-02-18",
      "gameicon": "https://cdn2.steamgriddb.com/icon_thumb/b9a8f4af85454f7c56c06f0a39e7ec23.png",
      "playtime": 325,
      "isDownload": false,
      "category": "2d",
      "gridPhoto": "https://cdn2.steamgriddb.com/thumb/aa595946cb2df920667a514d16be0c2e.jpg",
      "lasttwoweeks": 286,
      "gameDetailPhoto": "https://cdn2.steamgriddb.com/hero_thumb/4d19b37a2c399deace9082d464930022.jpg",
      "achievement": 7,
      "totalachievement": 102,
      "size": 49321,
      "isInProgress": false,
      "inQueue": false,
      "resize": 0,
      "reid": 1048
    },
    {
      "id": 50,
      "name": "Borderlands 3",
      "date": "2024-02-19",
      "gameicon": "https://cdn2.steamgriddb.com/hero_thumb/90664f7d1cde0398e10c9466ef495b89.jpg",
      "playtime": 335,
      "isDownload": false,
      "category": "uncategorized",
      "gridPhoto": "https://cdn2.steamgriddb.com/thumb/db56d3c9a49176ccd92b63c96c9facd8.jpg",
      "lasttwoweeks": 83,
      "gameDetailPhoto": "https://cdn2.steamgriddb.com/hero_thumb/90664f7d1cde0398e10c9466ef495b89.jpg",
      "achievement": 3,
      "totalachievement": 15,
      "size": 11584,
      "isInProgress": false,
      "inQueue": false,
      "resize": 0,
      "reid": 1049
    },
    {
      "id": 51,
      "name": "Among Us",
      "date": "2024-02-20",
      "gameicon": "https://cdn2.steamgriddb.com/icon_thumb/086af6e4641abb18caafc151b9aa95c8.png",
      "playtime": 345,
      "isDownload": true,
      "category": "favorite",
      "gridPhoto": "https://cdn2.steamgriddb.com/thumb/42acab51cf2973d1b174ec59f11c9795.jpg",
      "lasttwoweeks": 261,
      "gameDetailPhoto": "https://cdn2.steamgriddb.com/hero_thumb/4afa2aea8aa76eddf65a3b2c12a8f5f6.jpg",
      "achievement": 16,
      "totalachievement": 87,
      "size": 46658,
      "isInProgress": false,
      "inQueue": false,
      "resize": 25685,
      "reid": 1050
    },
    {
      "id": 52,
      "name": "Rocket League",
      "date": "2024-02-21",
      "gameicon": "https://cdn2.steamgriddb.com/icon/f1e513f02d2dbe70b939178cb7d4fbac/32/1024x1024.png",
      "playtime": 355,
      "isDownload": false,
      "category": "favorite",
      "gridPhoto": "https://cdn2.steamgriddb.com/thumb/a94595e22a11a0e271943269b1605e8d.jpg",
      "lasttwoweeks": 194,
      "gameDetailPhoto": "https://cdn2.steamgriddb.com/hero_thumb/e6da32eef072f987685b6eddca072d4f.jpg",
      "achievement": 132,
      "totalachievement": 149,
      "size": 71984,
      "isInProgress": false,
      "inQueue": false,
      "resize": 0,
      "reid": 1051
    },
    {
      "id": 53,
      "name": "Fallout 4",
      "date": "2024-02-22",
      "gameicon": "https://cdn2.steamgriddb.com/icon/73640de25b7d656733ce2f808a330f18/32/256x256.png",
      "playtime": 365,
      "isDownload": false,
      "category": "2d",
      "gridPhoto": "https://cdn2.steamgriddb.com/thumb/cd0f7919b441e9bb94c2308a8a5cfaea.jpg",
      "lasttwoweeks": 221,
      "gameDetailPhoto": "https://cdn2.steamgriddb.com/hero_thumb/6333712350d3e3751421dc8558f12608.jpg",
      "achievement": 0,
      "totalachievement": 7,
      "size": 85182,
      "isInProgress": false,
      "inQueue": false,
      "resize": 0,
      "reid": 1052
    },
    {
      "id": 54,
      "name": "Hades",
      "date": "2024-02-23",
      "gameicon": "https://cdn2.steamgriddb.com/icon/851300ee84c2b80ed40f51ed26d866fc/32/256x256.png",
      "playtime": 375,
      "isDownload": false,
      "category": "roleplay",
      "gridPhoto": "https://cdn2.steamgriddb.com/thumb/bfe339860b048949369fc6945cea504d.jpg",
      "lasttwoweeks": 268,
      "gameDetailPhoto": "https://cdn2.steamgriddb.com/hero_thumb/d9ac1fc532da6646901e9b30ba8964dd.jpg",
      "achievement": 29,
      "totalachievement": 37,
      "size": 76064,
      "isInProgress": false,
      "inQueue": false,
      "resize": 0,
      "reid": 1053
    },
    {
      "id": 55,
      "name": "Hollow Knight",
      "date": "2024-02-24",
      "gameicon": "https://cdn2.steamgriddb.com/icon/602d1305678a8d5fdb372271e980da6a/32/256x256.png",
      "playtime": 385,
      "isDownload": false,
      "category": "fps",
      "gridPhoto": "https://cdn2.steamgriddb.com/thumb/9be752bbca2828c70fd5d0afb6feec4d.jpg",
      "lasttwoweeks": 378,
      "gameDetailPhoto": "https://cdn2.steamgriddb.com/hero_thumb/e19099504769f3f7eb7e2f8b933db898.png",
      "achievement": 9,
      "totalachievement": 10,
      "size": 119507,
      "isInProgress": false,
      "inQueue": false,
      "resize": 0,
      "reid": 1054
    },
    {
      "id": 56,
      "name": "Slay the Spire",
      "date": "2024-02-25",
      "gameicon": "https://cdn2.steamgriddb.com/icon_thumb/649634bc7ca601b5907341f5df39f0a4.png",
      "playtime": 395,
      "isDownload": false,
      "category": "fps",
      "gridPhoto": "https://cdn2.steamgriddb.com/thumb/29ad31592cd288e1f793b8084d790002.jpg",
      "lasttwoweeks": 188,
      "gameDetailPhoto": "https://cdn2.steamgriddb.com/hero_thumb/5cfa02f9154d8220d0a911d6ca82ddb5.jpg",
      "achievement": 0,
      "totalachievement": 15,
      "size": 102307,
      "isInProgress": false,
      "inQueue": false,
      "resize": 0,
      "reid": 1055
    },
    {
      "id": 57,
      "name": "Dark Souls III",
      "date": "2024-02-26",
      "gameicon": "https://cdn2.steamgriddb.com/icon_thumb/649634bc7ca601b5907341f5df39f0a4.png",
      "playtime": 405,
      "isDownload": false,
      "category": "uncategorized",
      "gridPhoto": "https://cdn2.steamgriddb.com/thumb/bb375cd0b85fafbaea7a865130fc8e97.jpg",
      "lasttwoweeks": 326,
      "gameDetailPhoto": "https://cdn2.steamgriddb.com/hero_thumb/2578eb9cdf020730f77793e8b58e165a.jpg",
      "achievement": 8,
      "totalachievement": 22,
      "size": 59647,
      "isInProgress": false,
      "inQueue": false,
      "resize": 0,
      "reid": 1056
    },
    {
      "id": 58,
      "name": "DOOM Eternal",
      "date": "2024-02-27",
      "gameicon": "https://cdn2.steamgriddb.com/icon/9813b270ed0288e7c0388f0fd4ec68f5/32/512x512.png",
      "playtime": 415,
      "isDownload": false,
      "category": "fps",
      "gridPhoto": "https://cdn2.steamgriddb.com/thumb/f153536de78c7a703e40098ff497a1e0.jpg",
      "lasttwoweeks": 135,
      "gameDetailPhoto": "https://cdn2.steamgriddb.com/hero_thumb/9ce3d416394a5c9a29756027ff8cb37a.jpg",
      "achievement": 3,
      "totalachievement": 82,
      "size": 19282,
      "isInProgress": false,
      "inQueue": false,
      "resize": 0,
      "reid": 1057
    },
    {
      "id": 59,
      "name": "Valheim",
      "date": "2024-02-28",
      "gameicon": "https://cdn2.steamgriddb.com/icon/dd055f53a45702fe05e449c30ac80df9/32/256x256.png",
      "playtime": 425,
      "isDownload": false,
      "category": "2d",
      "gridPhoto": "https://cdn2.steamgriddb.com/thumb/c39a7edea71c7c9fb626d5466a9c5a9c.jpg",
      "lasttwoweeks": 127,
      "gameDetailPhoto": "https://cdn2.steamgriddb.com/hero_thumb/41c5d1b3d528eb912e486ad35dfaec92.jpg",
      "achievement": 81,
      "totalachievement": 112,
      "size": 44354,
      "isInProgress": false,
      "inQueue": false,
      "resize": 0,
      "reid": 1058
    },
    {
      "id": 60,
      "name": "Subnautica",
      "date": "2024-02-29",
      "gameicon": "https://cdn2.steamgriddb.com/icon_thumb/969ebecd17b888ab767fff8d3d894c2d.png",
      "playtime": 435,
      "isDownload": false,
      "category": "roleplay",
      "gridPhoto": "https://cdn2.steamgriddb.com/thumb/cb88c85733fd8241b9190750318f1e59.jpg",
      "lasttwoweeks": 384,
      "gameDetailPhoto": "https://cdn2.steamgriddb.com/hero_thumb/d94fd74dcde1aa553be72c1006578b23.jpg",
      "achievement": 14,
      "totalachievement": 68,
      "size": 93061,
      "isInProgress": false,
      "inQueue": false,
      "resize": 0,
      "reid": 1059
    },
    {
      "id": 61,
      "name": "Factorio",
      "date": "2024-03-01",
      "gameicon": "https://cdn2.steamgriddb.com/icon/6ca4e9af5ea662a095c3243dc591bf54/32/256x256.png",
      "playtime": 445,
      "isDownload": false,
      "category": "uncategorized",
      "gridPhoto": "https://cdn2.steamgriddb.com/thumb/0ded6348389f35483e961d04d7babcc8.jpg",
      "lasttwoweeks": 45,
      "gameDetailPhoto": "https://cdn2.steamgriddb.com/hero_thumb/e2d52448d36918c575fa79d88647ba66.jpg",
      "achievement": 7,
      "totalachievement": 9,
      "size": 59197,
      "isInProgress": false,
      "inQueue": false,
      "resize": 0,
      "reid": 1060
    },
    {
      "id": 62,
      "name": "Divinity: Original Sin 2",
      "date": "2024-03-02",
      "gameicon": "https://cdn2.steamgriddb.com/icon/ecd62de20ea67e1c2d933d311b08178a/32/256x256.png",
      "playtime": 455,
      "isDownload": false,
      "category": "uncategorized",
      "gridPhoto": "https://cdn2.steamgriddb.com/thumb/9f14875e20f4fd94cd92f48066a8ebe5.jpg",
      "lasttwoweeks": 438,
      "gameDetailPhoto": "https://cdn2.steamgriddb.com/hero_thumb/894d4b4665b798cc65d67cd6a32706aa.jpg",
      "achievement": 1,
      "totalachievement": 5,
      "size": 37651,
      "isInProgress": false,
      "inQueue": false,
      "resize": 0,
      "reid": 1061
    },
    {
      "id": 63,
      "name": "No Man's Sky",
      "date": "2024-03-03",
      "gameicon": "https://cdn2.steamgriddb.com/icon/61cb6463141119abd41762825ad4f9cd/32/256x256.png",
      "playtime": 465,
      "isDownload": false,
      "category": "fps",
      "gridPhoto": "https://cdn2.steamgriddb.com/thumb/a0790fa4aed5ce3a68901eab3e3bcf4c.png",
      "lasttwoweeks": 303,
      "gameDetailPhoto": "https://cdn2.steamgriddb.com/hero_thumb/8affe5b7d527c01b3a287168bb4439f6.jpg",
      "achievement": 40,
      "totalachievement": 52,
      "size": 43567,
      "isInProgress": false,
      "inQueue": false,
      "resize": 0,
      "reid": 1062
    },
    {
      "id": 64,
      "name": "Risk of Rain 2",
      "date": "2024-03-04",
      "gameicon": "https://cdn2.steamgriddb.com/icon/c4492cbe90fbdbf88a5aec486aa81ed5/32/256x256.png",
      "playtime": 475,
      "isDownload": false,
      "category": "uncategorized",
      "gridPhoto": "https://cdn2.steamgriddb.com/thumb/1486cfc241b063ca3589a17c09ef19c7.jpg",
      "lasttwoweeks": 20,
      "gameDetailPhoto": "https://cdn2.steamgriddb.com/hero_thumb/8affe5b7d527c01b3a287168bb4439f6.jpg",
      "achievement": 1,
      "totalachievement": 9,
      "size": 118298,
      "isInProgress": false,
      "inQueue": false,
      "resize": 0,
      "reid": 1063
    },
    {
      "id": 65,
      "name": "Deep Rock Galactic",
      "date": "2024-03-05",
      "gameicon": "https://cdn2.steamgriddb.com/icon/fb508ef074ee78a0e58c68be06d8a2eb/32/256x256.png",
      "playtime": 485,
      "isDownload": false,
      "category": "uncategorized",
      "gridPhoto": "https://cdn2.steamgriddb.com/thumb/1171384b3e11362c2460fbe30ad3e1e6.jpg",
      "lasttwoweeks": 37,
      "gameDetailPhoto": "https://cdn2.steamgriddb.com/hero_thumb/6345a8841a72751d7a407a8cdb2b1111.jpg",
      "achievement": 46,
      "totalachievement": 138,
      "size": 23819,
      "isInProgress": false,
      "inQueue": false,
      "resize": 0,
      "reid": 1064
    },
    {
      "id": 66,
      "name": "Kerbal Space Program",
      "date": "2024-03-06",
      "gameicon": "https://cdn2.steamgriddb.com/icon_thumb/2ee4162f4a89db5fa43b3b08900ee370.png",
      "playtime": 495,
      "isDownload": false,
      "category": "roleplay",
      "gridPhoto": "https://cdn2.steamgriddb.com/thumb/9f271b68ff7ba6511172ccdef214b0cf.jpg",
      "lasttwoweeks": 448,
      "gameDetailPhoto": "https://cdn2.steamgriddb.com/hero_thumb/6e3971ab57f150a2d2f359f60fa684bd.jpg",
      "achievement": 103,
      "totalachievement": 122,
      "size": 19774,
      "isInProgress": false,
      "inQueue": false,
      "resize": 0,
      "reid": 1065
    },
    {
      "id": 67,
      "name": "Halo Infinite",
      "date": "2024-03-07",
      "gameicon": "https://cdn2.steamgriddb.com/icon/f52166cd701447355be87cbf41d31ca4/32/256x256.png",
      "playtime": 505,
      "isDownload": false,
      "category": "2d",
      "gridPhoto": "https://cdn2.steamgriddb.com/thumb/0704f69bf721e74e98cbf1ed02223004.jpg",
      "lasttwoweeks": 82,
      "gameDetailPhoto": "https://cdn2.steamgriddb.com/hero_thumb/f633469121cb1895ba8023439e8197df.jpg",
      "achievement": 76,
      "totalachievement": 142,
      "size": 59241,
      "isInProgress": false,
      "inQueue": false,
      "resize": 0,
      "reid": 1066
    },
    {
      "id": 68,
      "name": "HITMAN 3",
      "date": "2024-03-08",
      "gameicon": "https://cdn2.steamgriddb.com/icon_thumb/217e342fc01668b10cb1188d40d3370e.png",
      "playtime": 515,
      "isDownload": false,
      "category": "uncategorized",
      "gridPhoto": "https://cdn2.steamgriddb.com/thumb/229118b6b5ec48bd139405e378234df9.jpg",
      "lasttwoweeks": 6,
      "gameDetailPhoto": "https://cdn2.steamgriddb.com/hero_thumb/f220707c3afe39d1779e0a34af72bb7f.jpg",
      "achievement": 11,
      "totalachievement": 88,
      "size": 110069,
      "isInProgress": false,
      "inQueue": false,
      "resize": 0,
      "reid": 1067
    },
    {
      "id": 69,
      "name": "Metro Exodus",
      "date": "2024-03-09",
      "gameicon": "https://cdn2.steamgriddb.com/icon/5da713a690c067105aeb2fae32403405/32/256x256.png",
      "playtime": 525,
      "isDownload": false,
      "category": "uncategorized",
      "gridPhoto": "https://cdn2.steamgriddb.com/thumb/07c15d7c3413da2ba77fbb56ac01a589.jpg",
      "lasttwoweeks": 159,
      "gameDetailPhoto": "https://cdn2.steamgriddb.com/hero_thumb/08425b881bcde94a383cd258cea331be.jpg",
      "achievement": 76,
      "totalachievement": 81,
      "size": 33384,
      "isInProgress": false,
      "inQueue": false,
      "resize": 0,
      "reid": 1068
    },
    {
      "id": 70,
      "name": "Control",
      "date": "2024-03-10",
      "gameicon": "https://cdn2.steamgriddb.com/icon/7716d0fc31636914783865d34f6cdfd5/32/256x256.png",
      "playtime": 535,
      "isDownload": false,
      "category": "2d",
      "gridPhoto": "https://cdn2.steamgriddb.com/thumb/b9b1d5684eed734c593a2cb81a5069d7.jpg",
      "lasttwoweeks": 146,
      "gameDetailPhoto": "https://cdn2.steamgriddb.com/hero_thumb/f4a9a68e297332af20b8abf5c7321756.jpg",
      "achievement": 96,
      "totalachievement": 132,
      "size": 26969,
      "isInProgress": false,
      "inQueue": false,
      "resize": 0,
      "reid": 1069
    },
    {
      "id": 71,
      "name": "Assassin's Creed Odyssey",
      "date": "2024-03-11",
      "gameicon": "https://cdn2.steamgriddb.com/icon_thumb/92f64fe558637b3139036adb8d5ecd14.png",
      "playtime": 545,
      "isDownload": false,
      "category": "favorite",
      "gridPhoto": "https://cdn2.steamgriddb.com/thumb/132d16811e7db45a5c501541c275851c.jpg",
      "lasttwoweeks": 217,
      "gameDetailPhoto": "https://cdn2.steamgriddb.com/hero_thumb/cc40d06ff0a16a793d066dbfa2917bab.jpg",
      "achievement": 23,
      "totalachievement": 44,
      "size": 114997,
      "isInProgress": false,
      "inQueue": false,
      "resize": 0,
      "reid": 1070
    },
    {
      "id": 72,
      "name": "Ghostrunner",
      "date": "2024-03-12",
      "gameicon": "https://cdn2.steamgriddb.com/icon/980a875ff6ef9c2d75e74307cbf5d205/32/256x256.png",
      "playtime": 555,
      "isDownload": false,
      "category": "uncategorized",
      "gridPhoto": "https://cdn2.steamgriddb.com/thumb/7203979920b9eb3a382fe3aae3968ea8.jpg",
      "lasttwoweeks": 98,
      "gameDetailPhoto": "https://cdn2.steamgriddb.com/hero_thumb/531d29a813ef9471aad0a5558d449a73.jpg",
      "achievement": 37,
      "totalachievement": 150,
      "size": 43277,
      "isInProgress": false,
      "inQueue": false,
      "resize": 0,
      "reid": 1071
    },
    {
      "id": 74,
      "name": "The Division 2",
      "date": "2024-03-14",
      "gameicon": "https://cdn2.steamgriddb.com/icon/3812f9a59b634c2a9c574610eaba5bed/32/256x256.png",
      "playtime": 575,
      "isDownload": false,
      "category": "2d",
      "gridPhoto": "https://cdn2.steamgriddb.com/thumb/ab6e6f39240d7dc6387a0f2e0efc148e.jpg",
      "lasttwoweeks": 162,
      "gameDetailPhoto": "https://cdn2.steamgriddb.com/hero_thumb/de7092ba6df4276921d27a3704c57998.jpg",
      "achievement": 11,
      "totalachievement": 88,
      "size": 75441,
      "isInProgress": false,
      "inQueue": false,
      "resize": 0,
      "reid": 1072
    },
    {
      "id": 75,
      "name": "Warframe",
      "date": "2024-03-15",
      "gameicon": "https://cdn2.steamgriddb.com/icon/83adc9225e4deb67d7ce42d58fe5157c/32/256x256.png",
      "playtime": 585,
      "isDownload": false,
      "category": "roleplay",
      "gridPhoto": "https://cdn2.steamgriddb.com/thumb/04766957db82a24eaa3006fb015798ba.jpg",
      "lasttwoweeks": 522,
      "gameDetailPhoto": "https://cdn2.steamgriddb.com/hero_thumb/b25b911ffc2b76a647454e5a53edf8b5.jpg",
      "achievement": 15,
      "totalachievement": 138,
      "size": 86100,
      "isInProgress": false,
      "inQueue": false,
      "resize": 0,
      "reid": 1073
    },
    {
      "id": 76,
      "name": "XCOM 2",
      "date": "2024-03-16",
      "gameicon": "https://cdn2.steamgriddb.com/icon_thumb/dd4143061640d55fb312dd0ce8afa76e.png",
      "playtime": 595,
      "isDownload": false,
      "category": "uncategorized",
      "gridPhoto": "https://cdn2.steamgriddb.com/thumb/81fa8ad16b19f8cd9091408b15570f14.png",
      "lasttwoweeks": 147,
      "gameDetailPhoto": "https://cdn2.steamgriddb.com/hero_thumb/c2148796071914983ed6b6e9dbbff735.jpg",
      "achievement": 24,
      "totalachievement": 53,
      "size": 95363,
      "isInProgress": false,
      "inQueue": false,
      "resize": 0,
      "reid": 1074
    },
    {
      "id": 77,
      "name": "Biomutant",
      "date": "2024-03-17",
      "gameicon": "https://cdn2.steamgriddb.com/icon_thumb/30ac4c52bd5bf0762504d49ecb92077d.png",
      "playtime": 605,
      "isDownload": false,
      "category": "roleplay",
      "gridPhoto": "https://cdn2.steamgriddb.com/thumb/eaebe20b3b8d24ed811f647df9f3068c.jpg",
      "lasttwoweeks": 307,
      "gameDetailPhoto": "https://cdn2.steamgriddb.com/hero_thumb/3d6506f8e91b91b051c8f1d956c4429f.jpg",
      "achievement": 37,
      "totalachievement": 67,
      "size": 66299,
      "isInProgress": false,
      "inQueue": false,
      "resize": 0,
      "reid": 1075
    },
    {
      "id": 78,
      "name": "Sekiro",
      "date": "2024-03-18",
      "gameicon": "https://cdn2.steamgriddb.com/icon/72e0a400c7b6e0beb7f2992c5378b3f6/32/256x256.png",
      "playtime": 615,
      "isDownload": false,
      "category": "uncategorized",
      "gridPhoto": "https://cdn2.steamgriddb.com/thumb/eaebe20b3b8d24ed811f647df9f3068c.jpg",
      "lasttwoweeks": 80,
      "gameDetailPhoto": "https://cdn2.steamgriddb.com/hero_thumb/2ee2b71a912ddc28699435eca8bd6486.jpg",
      "achievement": 93,
      "totalachievement": 116,
      "size": 66643,
      "isInProgress": false,
      "inQueue": false,
      "resize": 0,
      "reid": 1076
    },
    {
      "id": 79,
      "name": "GreedFall",
      "date": "2024-03-19",
      "gameicon": "https://cdn2.steamgriddb.com/icon/71aed24aa9e22bcd3516ba73c291aa18/32/512x512.png",
      "playtime": 625,
      "isDownload": false,
      "category": "uncategorized",
      "gridPhoto": "https://cdn2.steamgriddb.com/thumb/a1e1a0ec0c568e227dc51b37604aa218.jpg",
      "lasttwoweeks": 472,
      "gameDetailPhoto": "https://cdn2.steamgriddb.com/hero_thumb/02b0c69e363112f8c2d553a48a894db8.jpg",
      "achievement": 63,
      "totalachievement": 135,
      "size": 117257,
      "isInProgress": false,
      "inQueue": false,
      "resize": 0,
      "reid": 1077
    },
    {
      "id": 80,
      "name": "Code Vein",
      "date": "2024-03-20",
      "gameicon": "https://cdn2.steamgriddb.com/icon/d77e68596c15c53c2a33ad143739902d/32/256x256.png",
      "playtime": 635,
      "isDownload": false,
      "category": "2d",
      "gridPhoto": "https://cdn2.steamgriddb.com/thumb/6fe0d5701051209460f866acec5a283a.jpg",
      "lasttwoweeks": 590,
      "gameDetailPhoto": "https://cdn2.steamgriddb.com/hero_thumb/0bd81786a8ec6ae9b22cbb3cb4d88179.jpg",
      "achievement": 71,
      "totalachievement": 120,
      "size": 93768,
      "isInProgress": false,
      "inQueue": false,
      "resize": 0,
      "reid": 1078
    },
    {
      "id": 81,
      "name": "Death Stranding",
      "date": "2024-03-21",
      "gameicon": "https://cdn2.steamgriddb.com/icon/0c1c995b77ea7312f887ddd9f9d35de5/32/256x256.png",
      "playtime": 645,
      "isDownload": false,
      "category": "roleplay",
      "gridPhoto": "https://cdn2.steamgriddb.com/thumb/6b0173262b1ac7f6c1937c79cf03147b.jpg",
      "lasttwoweeks": 614,
      "gameDetailPhoto": "https://cdn2.steamgriddb.com/hero_thumb/384babc3e7faa44cf1ca671b74499c3b.jpg",
      "achievement": 29,
      "totalachievement": 122,
      "size": 72289,
      "isInProgress": false,
      "inQueue": false,
      "resize": 0,
      "reid": 1079
    },
    {
      "id": 82,
      "name": "Horizon Zero Dawn",
      "date": "2024-03-22",
      "gameicon": "https://cdn2.steamgriddb.com/icon_thumb/1ac065e393605e57f3eb01f535522c98.png",
      "playtime": 655,
      "isDownload": false,
      "category": "roleplay",
      "gridPhoto": "https://cdn2.steamgriddb.com/thumb/abd673b91e4bb9c556da84c6f6f5d470.jpg",
      "lasttwoweeks": 517,
      "gameDetailPhoto": "https://cdn2.steamgriddb.com/hero_thumb/67ba02d73c54f0b83c05507b7fb7267f.jpg",
      "achievement": 67,
      "totalachievement": 87,
      "size": 52982,
      "isInProgress": false,
      "inQueue": false,
      "resize": 0,
      "reid": 1080
    },
    {
      "id": 83,
      "name": "F1 2021",
      "date": "2024-03-23",
      "gameicon": "https://cdn2.steamgriddb.com/icon_thumb/8ff3fdef6f5144f50eb2a83cd34baa5d.png",
      "playtime": 665,
      "isDownload": false,
      "category": "uncategorized",
      "gridPhoto": "https://cdn2.steamgriddb.com/thumb/d4c1a2ad204bb3ff7e082b7b8a43164d.jpg",
      "lasttwoweeks": 613,
      "gameDetailPhoto": "https://cdn2.steamgriddb.com/hero_thumb/cda95cf018c449a29def6c95a0bf8db5.jpg",
      "achievement": 11,
      "totalachievement": 14,
      "size": 59009,
      "isInProgress": false,
      "inQueue": false,
      "resize": 0,
      "reid": 1081
    },
    {
      "id": 84,
      "name": "The Medium",
      "date": "2024-03-24",
      "gameicon": "https://cdn2.steamgriddb.com/icon_thumb/34e0ace0f37f8857eba8e3531c96fa06.png",
      "playtime": 675,
      "isDownload": false,
      "category": "uncategorized",
      "gridPhoto": "https://cdn2.steamgriddb.com/thumb/dd1d9b4d75bef47ca961180f6ad1941d.jpg",
      "lasttwoweeks": 37,
      "gameDetailPhoto": "https://cdn2.steamgriddb.com/hero_thumb/f9cb3124b5a22b133f21273ef2cb0695.jpg",
      "achievement": 33,
      "totalachievement": 123,
      "size": 49560,
      "isInProgress": false,
      "inQueue": false,
      "resize": 0,
      "reid": 1082
    },
    {
      "id": 85,
      "name": "Marvel's Avengers",
      "date": "2024-03-25",
      "gameicon": "https://cdn2.steamgriddb.com/icon/64504114e79857fb3d0b040489618c14/32/256x256.png",
      "playtime": 685,
      "isDownload": false,
      "category": "2d",
      "gridPhoto": "https://cdn2.steamgriddb.com/thumb/f613252eccacc564fb3335167380efb7.jpg",
      "lasttwoweeks": 504,
      "gameDetailPhoto": "https://cdn2.steamgriddb.com/hero_thumb/7e44f6169f0ae75b943cafb5acdb4449.jpg",
      "achievement": 35,
      "totalachievement": 60,
      "size": 36494,
      "isInProgress": false,
      "inQueue": false,
      "resize": 0,
      "reid": 1083
    },
    {
      "id": 86,
      "name": "Watch Dogs: Legion",
      "date": "2024-03-26",
      "gameicon": "https://cdn2.steamgriddb.com/icon/28c3fd8e66dae32e2ab61810ae2133e1/32/128x128.png",
      "playtime": 695,
      "isDownload": false,
      "category": "roleplay",
      "gridPhoto": "https://cdn2.steamgriddb.com/thumb/96100650570fb5db238f9dd73cc161af.jpg",
      "lasttwoweeks": 218,
      "gameDetailPhoto": "https://cdn2.steamgriddb.com/hero_thumb/5f1db7a13730fea2764ea1c0a3de2939.jpg",
      "achievement": 2,
      "totalachievement": 7,
      "size": 30587,
      "isInProgress": false,
      "inQueue": false,
      "resize": 0,
      "reid": 1084
    },
    {
      "id": 87,
      "name": "Immortals Fenyx Rising",
      "date": "2024-03-27",
      "gameicon": "https://cdn2.steamgriddb.com/icon/9b9236c6d892bd929385745701615190/32/256x256.png",
      "playtime": 705,
      "isDownload": false,
      "category": "uncategorized",
      "gridPhoto": "https://cdn2.steamgriddb.com/thumb/8d0e391b5e9743ba7824b1eceef9271e.jpg",
      "lasttwoweeks": 142,
      "gameDetailPhoto": "https://cdn2.steamgriddb.com/hero_thumb/8c317a7c6c3e9bd6382554ce9f0811aa.jpg",
      "achievement": 7,
      "totalachievement": 9,
      "size": 93444,
      "isInProgress": false,
      "inQueue": false,
      "resize": 0,
      "reid": 1085
    },
    {
      "id": 88,
      "name": "Microsoft Flight Simulator",
      "date": "2024-03-28",
      "gameicon": "https://cdn2.steamgriddb.com/icon_thumb/a37274fe2268a119c3fe913af5446ad9.png",
      "playtime": 715,
      "isDownload": false,
      "category": "uncategorized",
      "gridPhoto": "https://cdn2.steamgriddb.com/thumb/ee3d844bb81bd3565dacf5e720354048.jpg",
      "lasttwoweeks": 711,
      "gameDetailPhoto": "https://cdn2.steamgriddb.com/hero_thumb/2dc78e6026928309d3d26dc6dbd0276e.jpg",
      "achievement": 17,
      "totalachievement": 47,
      "size": 59740,
      "isInProgress": false,
      "inQueue": false,
      "resize": 0,
      "reid": 1086
    },
    {
      "id": 89,
      "name": "Grounded",
      "date": "2024-03-29",
      "gameicon": "https://cdn2.steamgriddb.com/icon/3aca5559a842cac6011c4fa97180a5f0/32/512x512.png",
      "playtime": 725,
      "isDownload": false,
      "category": "fps",
      "gridPhoto": "https://cdn2.steamgriddb.com/thumb/fde3da3f9b16fc522a12ed5fdfb347b3.jpg",
      "lasttwoweeks": 485,
      "gameDetailPhoto": "https://cdn2.steamgriddb.com/hero_thumb/b7e97864589bd572d706f436fa2eb387.jpg",
      "achievement": 79,
      "totalachievement": 84,
      "size": 58664,
      "isInProgress": false,
      "inQueue": false,
      "resize": 0,
      "reid": 1087
    },
    {
      "id": 90,
      "name": "Outer Wilds",
      "date": "2024-03-30",
      "gameicon": "https://cdn2.steamgriddb.com/icon/3e9202b0e44f3beceabe991c06dbcd2d/32/256x256.png",
      "playtime": 735,
      "isDownload": false,
      "category": "roleplay",
      "gridPhoto": "https://cdn2.steamgriddb.com/thumb/015f8780d976259d30135da2b8c420b2.jpg",
      "lasttwoweeks": 733,
      "gameDetailPhoto": "https://cdn2.steamgriddb.com/hero_thumb/1166db2e6b57e62146edee2f05a5c885.jpg",
      "achievement": 34,
      "totalachievement": 49,
      "size": 27791,
      "isInProgress": false,
      "inQueue": false,
      "resize": 0,
      "reid": 1088
    },
    {
      "id": 91,
      "name": "The Outer Worlds",
      "date": "2024-03-31",
      "gameicon": "https://cdn2.steamgriddb.com/icon_thumb/970b609f5323a8d2c83a555d39242bb9.png",
      "playtime": 745,
      "isDownload": false,
      "category": "uncategorized",
      "gridPhoto": "https://cdn2.steamgriddb.com/thumb/80624840efaf67e6753a23aa8b8345c5.jpg",
      "lasttwoweeks": 305,
      "gameDetailPhoto": "https://cdn2.steamgriddb.com/hero_thumb/242693e0e518a473d4374f84de433521.jpg",
      "achievement": 62,
      "totalachievement": 132,
      "size": 42724,
      "isInProgress": false,
      "inQueue": false,
      "resize": 0,
      "reid": 1089
    },
    {
      "id": 92,
      "name": "Sea of Thieves",
      "date": "2024-04-01",
      "gameicon": "https://cdn2.steamgriddb.com/icon/ed8a8a99fd79417dd5ee86e141fc2233/32/512x512.png",
      "playtime": 755,
      "isDownload": false,
      "category": "uncategorized",
      "gridPhoto": "https://cdn2.steamgriddb.com/thumb/1a1ec01f6458adecccb605200d42f47c.jpg",
      "lasttwoweeks": 489,
      "gameDetailPhoto": "https://cdn2.steamgriddb.com/hero_thumb/889fbd1aec443cef389ea10c93b498d8.jpg",
      "achievement": 19,
      "totalachievement": 71,
      "size": 30677,
      "isInProgress": false,
      "inQueue": false,
      "resize": 0,
      "reid": 1090
    },
    {
      "id": 93,
      "name": "Star Wars Jedi: Fallen Order",
      "date": "2024-04-02",
      "gameicon": "https://cdn2.steamgriddb.com/icon/2fd0fd3efa7c4cfb034317b21f3c2d93/32/256x256.png",
      "playtime": 765,
      "isDownload": false,
      "category": "uncategorized",
      "gridPhoto": "https://cdn2.steamgriddb.com/thumb/3205b3d0d7def309007edd6c22dd3339.jpg",
      "lasttwoweeks": 629,
      "gameDetailPhoto": "https://cdn2.steamgriddb.com/hero_thumb/4122cb13c7a474c1976c9706ae36521d.jpg",
      "achievement": 49,
      "totalachievement": 84,
      "size": 70703,
      "isInProgress": false,
      "inQueue": false,
      "resize": 0,
      "reid": 1091
    },
    {
      "id": 94,
      "name": "Dead Cells",
      "date": "2024-04-03",
      "gameicon": "https://cdn2.steamgriddb.com/icon_thumb/fe87435d12ef7642af67d9bc82a8b3cd.png",
      "playtime": 775,
      "isDownload": false,
      "category": "roleplay",
      "gridPhoto": "https://cdn2.steamgriddb.com/thumb/239ba3d13fc283598cfbe5dea91a928b.jpg",
      "lasttwoweeks": 593,
      "gameDetailPhoto": "https://cdn2.steamgriddb.com/hero_thumb/d0dde222e608c66b65d44776bd8b4092.jpg",
      "achievement": 14,
      "totalachievement": 138,
      "size": 100878,
      "isInProgress": false,
      "inQueue": false,
      "resize": 0,
      "reid": 1092
    },
    {
      "id": 95,
      "name": "Disco Elysium",
      "date": "2024-04-04",
      "gameicon": "https://cdn2.steamgriddb.com/icon/4ceefb51ae9ec399a69540c895f4519f/32/256x256.png",
      "playtime": 785,
      "isDownload": false,
      "category": "2d",
      "gridPhoto": "https://cdn2.steamgriddb.com/thumb/4b5c3939c79dcec4e477a14c4e343a66.jpg",
      "lasttwoweeks": 477,
      "gameDetailPhoto": "https://cdn2.steamgriddb.com/hero_thumb/7b16a52cf3727c22984590c4f4c36039.jpg",
      "achievement": 24,
      "totalachievement": 84,
      "size": 58925,
      "isInProgress": false,
      "inQueue": false,
      "resize": 0,
      "reid": 1093
    },
    {
      "id": 96,
      "name": "Ori and the Will of the Wisps",
      "date": "2024-04-05",
      "gameicon": "https://cdn2.steamgriddb.com/icon/12d6b5e5a791029b893bf3f08733aec2/32/256x256.png",
      "playtime": 795,
      "isDownload": false,
      "category": "roleplay",
      "gridPhoto": "https://cdn2.steamgriddb.com/thumb/7cd613b5798d0c540ba064c5f7ecc386.jpg",
      "lasttwoweeks": 617,
      "gameDetailPhoto": "https://cdn2.steamgriddb.com/hero_thumb/7f9b98141b2a0a95dcb5fc8a3dd4deae.jpg",
      "achievement": 35,
      "totalachievement": 44,
      "size": 41282,
      "isInProgress": false,
      "inQueue": false,
      "resize": 0,
      "reid": 1094
    },
    {
      "id": 97,
      "name": "Planet Zoo",
      "date": "2024-04-06",
      "gameicon": "https://cdn2.steamgriddb.com/icon_thumb/822b440edda4c46a5e1dad463eaf8ebd.png",
      "playtime": 805,
      "isDownload": false,
      "category": "2d",
      "gridPhoto": "https://cdn2.steamgriddb.com/thumb/ae0ab6d8be1aad8b3d9c6c332a32bddb.jpg",
      "lasttwoweeks": 539,
      "gameDetailPhoto": "https://cdn2.steamgriddb.com/hero_thumb/561ac63524680368701567891601024a.jpg",
      "achievement": 44,
      "totalachievement": 115,
      "size": 67493,
      "isInProgress": false,
      "inQueue": false,
      "resize": 0,
      "reid": 1095
    },
    {
      "id": 98,
      "name": "Total War: Three Kingdoms",
      "date": "2024-04-07",
      "gameicon": "https://i.hizliresim.com/44p6qss.jpg",
      "playtime": 815,
      "isDownload": false,
      "category": "uncategorized",
      "gridPhoto": "https://cdn2.steamgriddb.com/thumb/43dc32b5e9ebfc45bd4faf6e28d6ecd0.jpg",
      "lasttwoweeks": 305,
      "gameDetailPhoto": "https://cdn2.steamgriddb.com/hero_thumb/323799e616cdbe8f6d89d6a253e8f0fc.jpg",
      "achievement": 55,
      "totalachievement": 120,
      "size": 11406,
      "isInProgress": false,
      "inQueue": false,
      "resize": 0,
      "reid": 1096
    },
    {
      "id": 99,
      "name": "Yakuza: Like a Dragon",
      "date": "2024-04-08",
      "gameicon": "https://cdn2.steamgriddb.com/icon_thumb/5e6bd7a6970cd4325e587f02667f7f73.png",
      "playtime": 825,
      "isDownload": false,
      "category": "2d",
      "gridPhoto": "https://cdn2.steamgriddb.com/thumb/14b91c73a3b67f741d93122aaf961eec.jpg",
      "lasttwoweeks": 84,
      "gameDetailPhoto": "https://cdn2.steamgriddb.com/hero_thumb/b533868508ec8c95aeabdc36ecc28e79.jpg",
      "achievement": 30,
      "totalachievement": 99,
      "size": 20000,
      "isInProgress": false,
      "inQueue": false,
      "resize": 0,
      "reid": 1097
    }
  ]
}
